README.rst
setup.py
pm/__init__.py
pm/console.py
pm/memoized.py
pm/projects.py
pm.egg-info/PKG-INFO
pm.egg-info/SOURCES.txt
pm.egg-info/dependency_links.txt
pm.egg-info/entry_points.txt
pm.egg-info/top_level.txt
pm/scm/__init__.py
pm/scm/base.py
pm/scm/git.py
pm/scripts/__init__.py
pm/scripts/base.py
pm/scripts/pcd.py