Metadata-Version: 1.1
Name: pm
Version: 0.1
Summary: Command-line utility to manage development projects
Home-page: https://github.com/wichtounet/pm
Author: Baptiste Wicht
Author-email: baptiste.wicht@gmail.com
License: MIT
Download-URL: https://github.com/wichtounet/pm/tarball/0.1
Platform: UNKNOWN
